{  
   "case1":[
   	"Pens",
   	"Spectrum Case Key",
   	"Condensed milk",
   	"A cup of coffee",
   	"Gum \"Love is\"",
   	"USB Lamp",
   	"Nesquik",
   	"Alarm clock",
   	"Fan heater",
   	"MP3 player",
   	"Pizza",
   	"Burger"
    ],

   "case4":[ 
   	"Gut Knife - Damascus Steel",
   	"Gut Knife - Marble Fade",
   	"Shadow Daggers - Urban Masked",
   	"Flip Knife - Slaughter",
   	"Shadow Daggers - Fade",
   	"Falchion Knife - Damascus Steel",
   	"Bowie Knife - Fade",
   	"Karambit - Tiger Tooth",
   	"Huntsman Knife - Case Hardened",
   	"Bayonet - Autotronic",
   	"Bayonet - Black Laminate",
   	"M9 Bayonet - Lore",
   	"Karambit - Case Hardened"
   ],

   "case9":[ 
   	"Wismec Predator 228",
   	"Power Bank 5000mAh",
   	"Electric shaver Braun",
   	"Cable Xtorm Type-C USB",
   	"Spinner",
   	"USB flash drive 4 GB",
   	"Windows 10 Pro",
   	"Radio-controlled machine",
   	"Headphones",
   	"Coffee machine",
   	"Robot Vacuum Cleaner",
   	"GoPro HERO5",
   	"Sony PlayStation 4 Pro 1 TB",
   	"Microsoft Xbox One X 1 TB",
   	"Nvidia GeForce GTX 1080 Ti"
   ],

   "case10":[ 
   	"Kaspersky Anti-Virus",
   	"Key SW: Battlefront II - 4400 crystals",
   	"Saw Mask",
   	"Thermo mug",
   	"Monopod",
   	"USB flash drive 32 GB",
   	"Multi-function printer",
   	"Сomputer mouse Razer DeathAdder Elite",
   	"Airsoft Beretta M92",
   	"TV Haier LE42K5500TF",
   	"Watch G-SHOCK GA-1100-9G",
   	"Camera Canon 1300D",
   	"Monitor ASUS MG278Q",
   	"Apple iPad Gold 256 Гб"
   ],

   "case11":[ 
   	"Lighter Zippo",
   	"Fitness tracker HUAWEI Band 2 PRO",
   	"Cable Xtorm Type-C USB",
   	"USB hub",
   	"USB flash drive 4 GB",
   	"SSD 240 GB",
   	"Smart Watch",
   	"Headphones",
   	"Coffee machine",
   	"Hammer drill",
   	"Georosculator",
   	"Keyboard Corsair K95 RGB Platinum",
   	"Sony PlayStation 4 Pro 1 TB"
   ],

   "case12":[ 
   	"Mazda CX-5, 2017",
   	"BMW X4, 2017",
   	"Cadillac Escalade, 2016",
   	"Inspire 1 v2.0",
   	"Inspire 2 combo",
   	"Bayonet - Black Laminate",
   	"M9 Bayonet - Lore",
   	"Karambit - Case Hardened",
   	"T34",
   	"LÖWE",
   	"Bitcoin",
   	"Apple iPhone X 256 GB",
   	"ASUS ROG GX800VH",
   	"Sony PlayStation 4 Pro 1 TB",
   	"Microsoft Xbox One X 1 TB",
   	"Nvidia GeForce GTX 1080 Ti",
   	"Monitor ASUS MG278Q",
   	"Apple iPad Gold 256 GB"
   ]
}